{
  "url": "https://www.taniabulhoes.com.br/cuidados-pessoais",
  "title": "Cuidados Pessoais - Tania Bulhões",
  "sections": [
    {
      "selector": "header[data-sentry-element=\"unknown\"] > div.button-section",
      "attrs": {
        "class": "button-section"
      },
      "heading": "Ops, sua sacola está vazia!",
      "text_blocks": [
        "Veja nossas principais categorias",
        "perfumaria casa",
        "eau de parfum",
        "taniapele",
        "colecoes",
        "presentes"
      ],
      "images": [],
      "image_urls": [],
      "background_images": [],
      "videos": [],
      "video_urls": [],
      "html": null,
      "score": 322
    },
    {
      "selector": "html[data-sentry-component=\"RootLayout\"] > body:nth-of-type(1) > div:nth-of-type(3) > section.sc-ed6ed672-0.byBQkm > article:nth-of-type(1) > div.sc-b600379b-0.kEjiws",
      "attrs": {
        "data-sentry-element": "unknown",
        "data-sentry-source-file": "MegamenuDesktop.tsx",
        "class": "sc-b600379b-0 kEjiws"
      },
      "heading": null,
      "text_blocks": [
        "Seu Perfume Ideal",
        "Primeira Compra",
        "Lançamentos",
        "Best Sellers",
        "Premiados",
        "Para Viagem",
        "Fragrâncias",
        "Kits Presenteáveis",
        "Chá Branco",
        "Rosas Roubadas",
        "À Francesa",
        "Encontro Marcado",
        "Frenesi",
        "Ver Todos",
        "Mãos e Corpo",
        "Banho",
        "Hidratação",
        "Creme para Mãos",
        "Colônias para Cabelo"
      ],
      "images": [
        {
          "src": "https://static.taniabulhoes.com.br/STILL_KITS_PERFUMARIA_PROVENCE_DIA_DAS_MAES_0453_1_OK_3bb1002b64.jpg",
          "srcset": null,
          "best": "https://static.taniabulhoes.com.br/STILL_KITS_PERFUMARIA_PROVENCE_DIA_DAS_MAES_0453_1_OK_3bb1002b64.jpg",
          "alt": "Background image",
          "isBackground": true
        },
        {
          "src": "https://static.taniabulhoes.com.br/003_L02800143_Galeria_Olfativa_2_1f31f96456.jpg",
          "srcset": null,
          "best": "https://static.taniabulhoes.com.br/003_L02800143_Galeria_Olfativa_2_1f31f96456.jpg",
          "alt": "Background image",
          "isBackground": true
        },
        {
          "src": "https://static.taniabulhoes.com.br/003002800003_Frenesi_Eau_de_Parfum_80ml_ceada9b500.jpg",
          "srcset": null,
          "best": "https://static.taniabulhoes.com.br/003002800003_Frenesi_Eau_de_Parfum_80ml_ceada9b500.jpg",
          "alt": "Background image",
          "isBackground": true
        }
      ],
      "image_urls": [
        "https://static.taniabulhoes.com.br/STILL_KITS_PERFUMARIA_PROVENCE_DIA_DAS_MAES_0453_1_OK_3bb1002b64.jpg",
        "https://static.taniabulhoes.com.br/003_L02800143_Galeria_Olfativa_2_1f31f96456.jpg",
        "https://static.taniabulhoes.com.br/003002800003_Frenesi_Eau_de_Parfum_80ml_ceada9b500.jpg"
      ],
      "background_images": [
        "https://static.taniabulhoes.com.br/STILL_KITS_PERFUMARIA_PROVENCE_DIA_DAS_MAES_0453_1_OK_3bb1002b64.jpg",
        "https://static.taniabulhoes.com.br/003_L02800143_Galeria_Olfativa_2_1f31f96456.jpg",
        "https://static.taniabulhoes.com.br/003002800003_Frenesi_Eau_de_Parfum_80ml_ceada9b500.jpg"
      ],
      "videos": [],
      "video_urls": [],
      "html": null,
      "score": 1200
    },
    {
      "selector": "html[data-sentry-component=\"RootLayout\"] > body:nth-of-type(1) > div:nth-of-type(4) > section.sc-ed6ed672-0.lheTQi > article:nth-of-type(1) > div:nth-of-type(1)",
      "attrs": {},
      "heading": null,
      "text_blocks": [
        "mediterrâneo",
        "fênix",
        "perfumes",
        "provence",
        "marquesa",
        "aromatizadores"
      ],
      "images": [],
      "image_urls": [],
      "background_images": [],
      "videos": [],
      "video_urls": [],
      "html": null,
      "score": 140
    },
    {
      "selector": "html[data-sentry-component=\"RootLayout\"] > body:nth-of-type(1) > article:nth-of-type(1) > div:nth-of-type(2)",
      "attrs": {
        "class": "sc-7620ef51-2 hqpLLx"
      },
      "heading": null,
      "text_blocks": [
        "1989 Eau de Parfum",
        "Um floral fresco e envolvente",
        "Conheça"
      ],
      "images": [],
      "image_urls": [],
      "background_images": [],
      "videos": [],
      "video_urls": [],
      "html": null,
      "score": 136
    },
    {
      "selector": "#\\32 65",
      "attrs": {
        "id": "265",
        "data-sentry-element": "unknown",
        "data-sentry-component": "TemplateSection",
        "data-sentry-source-file": "TemplateSection.tsx",
        "class": "sc-70cd0c58-0 evgCYK"
      },
      "heading": "Inspire-se em nossos rituais de autocuidado",
      "text_blocks": [
        "Inspire-se em nossos rituais de autocuidado",
        "Estenda o poder da sua perfumação.",
        "Primeira Compra",
        "Colônia para Cabelo",
        "Mãos e Corpo",
        "Perfumes"
      ],
      "images": [
        {
          "src": "https://static.taniabulhoes.com.br/003_L02800143_Galeria_Olfativa_2_1f31f96456.jpg",
          "srcset": null,
          "best": "https://static.taniabulhoes.com.br/003_L02800143_Galeria_Olfativa_2_1f31f96456.jpg",
          "alt": null
        },
        {
          "src": "https://static.taniabulhoes.com.br/003_L02800143_Galeria_Olfativa_c9ad37775b.jpg",
          "srcset": null,
          "best": "https://static.taniabulhoes.com.br/003_L02800143_Galeria_Olfativa_c9ad37775b.jpg",
          "alt": "Primeira Compra"
        },
        {
          "src": "https://static.taniabulhoes.com.br/COLONIA_PARA_CABELO_CHA_BRANCO_2_cddf4568c5.jpg",
          "srcset": null,
          "best": "https://static.taniabulhoes.com.br/COLONIA_PARA_CABELO_CHA_BRANCO_2_cddf4568c5.jpg",
          "alt": null
        },
        {
          "src": "https://static.taniabulhoes.com.br/CREME_PARA_MAOS_CHA_BRANCO_2_e1d45c5a5f.jpg",
          "srcset": null,
          "best": "https://static.taniabulhoes.com.br/CREME_PARA_MAOS_CHA_BRANCO_2_e1d45c5a5f.jpg",
          "alt": "Colônia para Cabelo"
        },
        {
          "src": "https://static.taniabulhoes.com.br/768_x_1024_Caixa_Lavanda_2_57249b595c.jpg",
          "srcset": null,
          "best": "https://static.taniabulhoes.com.br/768_x_1024_Caixa_Lavanda_2_57249b595c.jpg",
          "alt": null
        },
        {
          "src": "https://static.taniabulhoes.com.br/STILL_PERFUMES_0468_OK_09a2640d19.jpg",
          "srcset": null,
          "best": "https://static.taniabulhoes.com.br/STILL_PERFUMES_0468_OK_09a2640d19.jpg",
          "alt": "Mãos e Corpo"
        },
        {
          "src": "https://static.taniabulhoes.com.br/5_178_OK_476d4854a2.jpg",
          "srcset": null,
          "best": "https://static.taniabulhoes.com.br/5_178_OK_476d4854a2.jpg",
          "alt": null
        },
        {
          "src": "https://static.taniabulhoes.com.br/BANNER_MOBILE_PERFUMES_8505303f83.jpg",
          "srcset": null,
          "best": "https://static.taniabulhoes.com.br/BANNER_MOBILE_PERFUMES_8505303f83.jpg",
          "alt": "Perfumes"
        }
      ],
      "image_urls": [
        "https://static.taniabulhoes.com.br/003_L02800143_Galeria_Olfativa_2_1f31f96456.jpg",
        "https://static.taniabulhoes.com.br/003_L02800143_Galeria_Olfativa_c9ad37775b.jpg",
        "https://static.taniabulhoes.com.br/COLONIA_PARA_CABELO_CHA_BRANCO_2_cddf4568c5.jpg",
        "https://static.taniabulhoes.com.br/CREME_PARA_MAOS_CHA_BRANCO_2_e1d45c5a5f.jpg",
        "https://static.taniabulhoes.com.br/768_x_1024_Caixa_Lavanda_2_57249b595c.jpg",
        "https://static.taniabulhoes.com.br/STILL_PERFUMES_0468_OK_09a2640d19.jpg",
        "https://static.taniabulhoes.com.br/5_178_OK_476d4854a2.jpg",
        "https://static.taniabulhoes.com.br/BANNER_MOBILE_PERFUMES_8505303f83.jpg"
      ],
      "background_images": [],
      "videos": [],
      "video_urls": [],
      "html": null,
      "score": 836
    },
    {
      "selector": "html[data-sentry-component=\"RootLayout\"] > body:nth-of-type(1) > article:nth-of-type(3)",
      "attrs": {
        "id": "double__template__container",
        "data-cy": "double-brand-section-container",
        "class": "sc-b44bab58-0 iNTOL"
      },
      "heading": "Sinta na pele e encante-se por nosso universo de sensações.",
      "text_blocks": [
        "Lançamentos",
        "Sinta na pele e encante-se por nosso universo de sensações.",
        "Veja Mais"
      ],
      "images": [
        {
          "src": "https://static.taniabulhoes.com.br/003_L01800033_K_Kit_Hidratante_Meu_Verde_150g_2_33859b96a4.jpg",
          "srcset": null,
          "best": "https://static.taniabulhoes.com.br/003_L01800033_K_Kit_Hidratante_Meu_Verde_150g_2_33859b96a4.jpg",
          "alt": "Background image",
          "isBackground": true
        },
        {
          "src": "https://static.taniabulhoes.com.br/003_L01800029_K_Kit_Hidratante_Cha_Branco_150g_4_b5dd7ddfe5.jpg",
          "srcset": null,
          "best": "https://static.taniabulhoes.com.br/003_L01800029_K_Kit_Hidratante_Cha_Branco_150g_4_b5dd7ddfe5.jpg",
          "alt": "Background image",
          "isBackground": true
        }
      ],
      "image_urls": [
        "https://static.taniabulhoes.com.br/003_L01800033_K_Kit_Hidratante_Meu_Verde_150g_2_33859b96a4.jpg",
        "https://static.taniabulhoes.com.br/003_L01800029_K_Kit_Hidratante_Cha_Branco_150g_4_b5dd7ddfe5.jpg"
      ],
      "background_images": [
        "https://static.taniabulhoes.com.br/003_L01800033_K_Kit_Hidratante_Meu_Verde_150g_2_33859b96a4.jpg",
        "https://static.taniabulhoes.com.br/003_L01800029_K_Kit_Hidratante_Cha_Branco_150g_4_b5dd7ddfe5.jpg"
      ],
      "videos": [],
      "video_urls": [],
      "html": null,
      "score": 1321
    },
    {
      "selector": "#\\32 61",
      "attrs": {
        "id": "261",
        "data-sentry-element": "unknown",
        "data-sentry-component": "TemplateSection",
        "data-sentry-source-file": "TemplateSection.tsx",
        "class": "sc-70cd0c58-0 evgCYK"
      },
      "heading": "Hidratantes",
      "text_blocks": [
        "Hidratantes",
        "Transforme seu cuidado diário em um gesto de prazer e sofisticação.",
        "Veludo Hidratante",
        "Creme para Mãos",
        "Kits de Perfumaria Pessoal"
      ],
      "images": [
        {
          "src": "https://static.taniabulhoes.com.br/STILL_KITS_PERFUMARIA_PROVENCE_DIA_DAS_MAES_0453_1_OK_c834771cd3.jpg",
          "srcset": null,
          "best": "https://static.taniabulhoes.com.br/STILL_KITS_PERFUMARIA_PROVENCE_DIA_DAS_MAES_0453_1_OK_c834771cd3.jpg",
          "alt": null
        },
        {
          "src": "https://static.taniabulhoes.com.br/Hidratantes_Corporal_878f12426c.jpg",
          "srcset": null,
          "best": "https://static.taniabulhoes.com.br/Hidratantes_Corporal_878f12426c.jpg",
          "alt": "Hidratantes"
        },
        {
          "src": "https://static.taniabulhoes.com.br/768_x_1024_Ventos_de_Lavanda_7eb8faa25f.jpg",
          "srcset": null,
          "best": "https://static.taniabulhoes.com.br/768_x_1024_Ventos_de_Lavanda_7eb8faa25f.jpg",
          "alt": null
        },
        {
          "src": "https://static.taniabulhoes.com.br/VELUDO_CHA_BRANCO_24d8828767.jpg",
          "srcset": null,
          "best": "https://static.taniabulhoes.com.br/VELUDO_CHA_BRANCO_24d8828767.jpg",
          "alt": "Veludo Hidratante"
        },
        {
          "src": "https://static.taniabulhoes.com.br/CREME_PARA_MAOS_CHA_BRANCO_2_055404670d.jpg",
          "srcset": null,
          "best": "https://static.taniabulhoes.com.br/CREME_PARA_MAOS_CHA_BRANCO_2_055404670d.jpg",
          "alt": null
        },
        {
          "src": "https://static.taniabulhoes.com.br/CREME_PARA_MAOS_CHA_BRANCO_7e90bdfd81.jpg",
          "srcset": null,
          "best": "https://static.taniabulhoes.com.br/CREME_PARA_MAOS_CHA_BRANCO_7e90bdfd81.jpg",
          "alt": "Creme para Mãos"
        },
        {
          "src": "https://static.taniabulhoes.com.br/003_L01800034_K_Kit_Hidratante_A_Francesa_150g_3_7490d3ab59.jpg",
          "srcset": null,
          "best": "https://static.taniabulhoes.com.br/003_L01800034_K_Kit_Hidratante_A_Francesa_150g_3_7490d3ab59.jpg",
          "alt": null
        },
        {
          "src": "https://static.taniabulhoes.com.br/003_L01800030_K_Kit_Hidratante_Ventos_de_Lavanda_150g_4_84324b4e41.jpg",
          "srcset": null,
          "best": "https://static.taniabulhoes.com.br/003_L01800030_K_Kit_Hidratante_Ventos_de_Lavanda_150g_4_84324b4e41.jpg",
          "alt": "Kits de Perfumaria Pessoal"
        }
      ],
      "image_urls": [
        "https://static.taniabulhoes.com.br/STILL_KITS_PERFUMARIA_PROVENCE_DIA_DAS_MAES_0453_1_OK_c834771cd3.jpg",
        "https://static.taniabulhoes.com.br/Hidratantes_Corporal_878f12426c.jpg",
        "https://static.taniabulhoes.com.br/768_x_1024_Ventos_de_Lavanda_7eb8faa25f.jpg",
        "https://static.taniabulhoes.com.br/VELUDO_CHA_BRANCO_24d8828767.jpg",
        "https://static.taniabulhoes.com.br/CREME_PARA_MAOS_CHA_BRANCO_2_055404670d.jpg",
        "https://static.taniabulhoes.com.br/CREME_PARA_MAOS_CHA_BRANCO_7e90bdfd81.jpg",
        "https://static.taniabulhoes.com.br/003_L01800034_K_Kit_Hidratante_A_Francesa_150g_3_7490d3ab59.jpg",
        "https://static.taniabulhoes.com.br/003_L01800030_K_Kit_Hidratante_Ventos_de_Lavanda_150g_4_84324b4e41.jpg"
      ],
      "background_images": [],
      "videos": [],
      "video_urls": [],
      "html": null,
      "score": 840
    },
    {
      "selector": "html[data-sentry-component=\"RootLayout\"] > body:nth-of-type(1) > article:nth-of-type(5)",
      "attrs": {
        "id": "double__template__container",
        "data-cy": "double-brand-section-container",
        "class": "sc-b44bab58-0 iNTOL"
      },
      "heading": "Acreditamos que a Eau de Parfum oferece a combinação perfeita de intensidade, longevidade, texturas e complexidade para as nossas criações olfativas.",
      "text_blocks": [
        "Descubra seu Perfume Ideal",
        "Acreditamos que a Eau de Parfum oferece a combinação perfeita de intensidade, longevidade, texturas e complexidade para as nossas criações olfativas.",
        "Conheça"
      ],
      "images": [
        {
          "src": "https://static.taniabulhoes.com.br/220125_TB_PERFUMARIA_2204_OK_1_956a02826b.jpg",
          "srcset": null,
          "best": "https://static.taniabulhoes.com.br/220125_TB_PERFUMARIA_2204_OK_1_956a02826b.jpg",
          "alt": "Background image",
          "isBackground": true
        },
        {
          "src": "https://static.taniabulhoes.com.br/230125_TB_PERFUMARIA_STILL_2387_OK_0d6cd72174.jpg",
          "srcset": null,
          "best": "https://static.taniabulhoes.com.br/230125_TB_PERFUMARIA_STILL_2387_OK_0d6cd72174.jpg",
          "alt": "Background image",
          "isBackground": true
        }
      ],
      "image_urls": [
        "https://static.taniabulhoes.com.br/220125_TB_PERFUMARIA_2204_OK_1_956a02826b.jpg",
        "https://static.taniabulhoes.com.br/230125_TB_PERFUMARIA_STILL_2387_OK_0d6cd72174.jpg"
      ],
      "background_images": [
        "https://static.taniabulhoes.com.br/220125_TB_PERFUMARIA_2204_OK_1_956a02826b.jpg",
        "https://static.taniabulhoes.com.br/230125_TB_PERFUMARIA_STILL_2387_OK_0d6cd72174.jpg"
      ],
      "videos": [],
      "video_urls": [],
      "html": null,
      "score": 1544
    },
    {
      "selector": "html[data-sentry-component=\"RootLayout\"] > body:nth-of-type(1) > article:nth-of-type(6)",
      "attrs": {
        "class": "sc-d3b38409-0 lbOpmB"
      },
      "heading": "Fragrâncias",
      "text_blocks": [
        "Fragrâncias",
        "Aventure-se por esse universo de fragrâncias excepcionais e vivencie a verdadeira arte da perfumaria.",
        "descubra",
        "Chá Branco",
        "Rosas Roubadas",
        "À Francesa",
        "Meu Verde",
        "Ventos de Lavanda",
        "Frenesi",
        "Encontro Marcado",
        "Fava Selvagem",
        "Sinfonia",
        "Segredo",
        "Meia-Noite"
      ],
      "images": [
        {
          "src": "https://static.taniabulhoes.com.br/000003015_Cha_Branco_Eau_de_Parfum_80ml_2_d6f39c630f.jpg",
          "srcset": null,
          "best": "https://static.taniabulhoes.com.br/000003015_Cha_Branco_Eau_de_Parfum_80ml_2_d6f39c630f.jpg",
          "alt": "Background image",
          "isBackground": true
        },
        {
          "src": "https://static.taniabulhoes.com.br/000003502_Rosas_Roubadas_Eau_de_Parfum_80ml_1d01905809.jpg",
          "srcset": null,
          "best": "https://static.taniabulhoes.com.br/000003502_Rosas_Roubadas_Eau_de_Parfum_80ml_1d01905809.jpg",
          "alt": "Background image",
          "isBackground": true
        },
        {
          "src": "https://static.taniabulhoes.com.br/000003011_1989_Eau_de_Parfum_80ml_1_b4d4db317b.jpg",
          "srcset": null,
          "best": "https://static.taniabulhoes.com.br/000003011_1989_Eau_de_Parfum_80ml_1_b4d4db317b.jpg",
          "alt": "Background image",
          "isBackground": true
        },
        {
          "src": "https://static.taniabulhoes.com.br/000003025_A_Francesa_Eau_de_Parfum_80ml_2_242a36d92e.jpg",
          "srcset": null,
          "best": "https://static.taniabulhoes.com.br/000003025_A_Francesa_Eau_de_Parfum_80ml_2_242a36d92e.jpg",
          "alt": "Background image",
          "isBackground": true
        },
        {
          "src": "https://static.taniabulhoes.com.br/000003019_Meu_Verde_Eau_de_Parfum_80ml_1_b0fd4eba42.jpg",
          "srcset": null,
          "best": "https://static.taniabulhoes.com.br/000003019_Meu_Verde_Eau_de_Parfum_80ml_1_b0fd4eba42.jpg",
          "alt": "Background image",
          "isBackground": true
        },
        {
          "src": "https://static.taniabulhoes.com.br/000003016_Ventos_de_Lavanda_Eau_de_Parfum_80ml_2_023975a9bd.jpg",
          "srcset": null,
          "best": "https://static.taniabulhoes.com.br/000003016_Ventos_de_Lavanda_Eau_de_Parfum_80ml_2_023975a9bd.jpg",
          "alt": "Background image",
          "isBackground": true
        },
        {
          "src": "https://static.taniabulhoes.com.br/003002800003_Frenesi_Eau_de_Parfum_80ml_11433463a0.jpg",
          "srcset": null,
          "best": "https://static.taniabulhoes.com.br/003002800003_Frenesi_Eau_de_Parfum_80ml_11433463a0.jpg",
          "alt": "Background image",
          "isBackground": true
        },
        {
          "src": "https://static.taniabulhoes.com.br/Encontro_Marcado_Eau_de_Parfum_80ml_2_1_7680e183ee.jpg",
          "srcset": null,
          "best": "https://static.taniabulhoes.com.br/Encontro_Marcado_Eau_de_Parfum_80ml_2_1_7680e183ee.jpg",
          "alt": "Background image",
          "isBackground": true
        },
        {
          "src": "https://static.taniabulhoes.com.br/000003026_Fava_Selvagem_Eau_de_Parfum_80ml_2_900275928d.jpg",
          "srcset": null,
          "best": "https://static.taniabulhoes.com.br/000003026_Fava_Selvagem_Eau_de_Parfum_80ml_2_900275928d.jpg",
          "alt": "Background image",
          "isBackground": true
        },
        {
          "src": "https://static.taniabulhoes.com.br/000003014_Sinfonia_Eau_de_Parfum_80ml_2_596c6fc737.jpg",
          "srcset": null,
          "best": "https://static.taniabulhoes.com.br/000003014_Sinfonia_Eau_de_Parfum_80ml_2_596c6fc737.jpg",
          "alt": "Background image",
          "isBackground": true
        },
        {
          "src": "https://static.taniabulhoes.com.br/000003024_Segredo_Eau_de_Parfum_80ml_1_b18cdd26b9.jpg",
          "srcset": null,
          "best": "https://static.taniabulhoes.com.br/000003024_Segredo_Eau_de_Parfum_80ml_1_b18cdd26b9.jpg",
          "alt": "Background image",
          "isBackground": true
        },
        {
          "src": "https://static.taniabulhoes.com.br/000003017_Meia_Noite_Eau_de_Parfum_80ml_1_0eef07fbce.jpg",
          "srcset": null,
          "best": "https://static.taniabulhoes.com.br/000003017_Meia_Noite_Eau_de_Parfum_80ml_1_0eef07fbce.jpg",
          "alt": "Background image",
          "isBackground": true
        }
      ],
      "image_urls": [
        "https://static.taniabulhoes.com.br/000003015_Cha_Branco_Eau_de_Parfum_80ml_2_d6f39c630f.jpg",
        "https://static.taniabulhoes.com.br/000003502_Rosas_Roubadas_Eau_de_Parfum_80ml_1d01905809.jpg",
        "https://static.taniabulhoes.com.br/000003011_1989_Eau_de_Parfum_80ml_1_b4d4db317b.jpg",
        "https://static.taniabulhoes.com.br/000003025_A_Francesa_Eau_de_Parfum_80ml_2_242a36d92e.jpg",
        "https://static.taniabulhoes.com.br/000003019_Meu_Verde_Eau_de_Parfum_80ml_1_b0fd4eba42.jpg",
        "https://static.taniabulhoes.com.br/000003016_Ventos_de_Lavanda_Eau_de_Parfum_80ml_2_023975a9bd.jpg",
        "https://static.taniabulhoes.com.br/003002800003_Frenesi_Eau_de_Parfum_80ml_11433463a0.jpg",
        "https://static.taniabulhoes.com.br/Encontro_Marcado_Eau_de_Parfum_80ml_2_1_7680e183ee.jpg",
        "https://static.taniabulhoes.com.br/000003026_Fava_Selvagem_Eau_de_Parfum_80ml_2_900275928d.jpg",
        "https://static.taniabulhoes.com.br/000003014_Sinfonia_Eau_de_Parfum_80ml_2_596c6fc737.jpg",
        "https://static.taniabulhoes.com.br/000003024_Segredo_Eau_de_Parfum_80ml_1_b18cdd26b9.jpg",
        "https://static.taniabulhoes.com.br/000003017_Meia_Noite_Eau_de_Parfum_80ml_1_0eef07fbce.jpg"
      ],
      "background_images": [
        "https://static.taniabulhoes.com.br/000003015_Cha_Branco_Eau_de_Parfum_80ml_2_d6f39c630f.jpg",
        "https://static.taniabulhoes.com.br/000003502_Rosas_Roubadas_Eau_de_Parfum_80ml_1d01905809.jpg",
        "https://static.taniabulhoes.com.br/000003011_1989_Eau_de_Parfum_80ml_1_b4d4db317b.jpg",
        "https://static.taniabulhoes.com.br/000003025_A_Francesa_Eau_de_Parfum_80ml_2_242a36d92e.jpg",
        "https://static.taniabulhoes.com.br/000003019_Meu_Verde_Eau_de_Parfum_80ml_1_b0fd4eba42.jpg",
        "https://static.taniabulhoes.com.br/000003016_Ventos_de_Lavanda_Eau_de_Parfum_80ml_2_023975a9bd.jpg",
        "https://static.taniabulhoes.com.br/003002800003_Frenesi_Eau_de_Parfum_80ml_11433463a0.jpg",
        "https://static.taniabulhoes.com.br/Encontro_Marcado_Eau_de_Parfum_80ml_2_1_7680e183ee.jpg",
        "https://static.taniabulhoes.com.br/000003026_Fava_Selvagem_Eau_de_Parfum_80ml_2_900275928d.jpg",
        "https://static.taniabulhoes.com.br/000003014_Sinfonia_Eau_de_Parfum_80ml_2_596c6fc737.jpg",
        "https://static.taniabulhoes.com.br/000003024_Segredo_Eau_de_Parfum_80ml_1_b18cdd26b9.jpg",
        "https://static.taniabulhoes.com.br/000003017_Meia_Noite_Eau_de_Parfum_80ml_1_0eef07fbce.jpg"
      ],
      "videos": [],
      "video_urls": [],
      "html": null,
      "score": 2164
    },
    {
      "selector": "#\\32 60",
      "attrs": {
        "id": "260",
        "data-sentry-element": "unknown",
        "data-sentry-component": "TemplateSection",
        "data-sentry-source-file": "TemplateSection.tsx",
        "class": "sc-70cd0c58-0 evgCYK"
      },
      "heading": "Explore as infinitas possibilidades olfativas e experimente combinações inusitadas",
      "text_blocks": [
        "Explore as infinitas possibilidades olfativas e experimente combinações inusitadas",
        "Para o Dia",
        "Para a Noite",
        "Best Sellers",
        "Premiados"
      ],
      "images": [
        {
          "src": "https://static.taniabulhoes.com.br/000003003_Meu_Verde_Eau_de_Parfum_30ml_2_29234c0234.jpg",
          "srcset": null,
          "best": "https://static.taniabulhoes.com.br/000003003_Meu_Verde_Eau_de_Parfum_30ml_2_29234c0234.jpg",
          "alt": null
        },
        {
          "src": "https://static.taniabulhoes.com.br/000003009_A_Francesa_Eau_de_Parfum_30ml_2_58cba84c8a.jpg",
          "srcset": null,
          "best": "https://static.taniabulhoes.com.br/000003009_A_Francesa_Eau_de_Parfum_30ml_2_58cba84c8a.jpg",
          "alt": "Para o Dia"
        },
        {
          "src": "https://static.taniabulhoes.com.br/000003010_Fava_Selvagem_Eau_de_Parfum_30ml_2_fe302c9fdb.jpg",
          "srcset": null,
          "best": "https://static.taniabulhoes.com.br/000003010_Fava_Selvagem_Eau_de_Parfum_30ml_2_fe302c9fdb.jpg",
          "alt": null
        },
        {
          "src": "https://static.taniabulhoes.com.br/Encontro_Marcado_Eau_de_Parfum_30ml_7b2fefd524.jpg",
          "srcset": null,
          "best": "https://static.taniabulhoes.com.br/Encontro_Marcado_Eau_de_Parfum_30ml_7b2fefd524.jpg",
          "alt": "Para a Noite"
        },
        {
          "src": "https://static.taniabulhoes.com.br/000003015_Cha_Branco_Eau_de_Parfum_80ml_2_d6f39c630f.jpg",
          "srcset": null,
          "best": "https://static.taniabulhoes.com.br/000003015_Cha_Branco_Eau_de_Parfum_80ml_2_d6f39c630f.jpg",
          "alt": null
        },
        {
          "src": "https://static.taniabulhoes.com.br/000003011_1989_Eau_de_Parfum_80ml_1_b4d4db317b.jpg",
          "srcset": null,
          "best": "https://static.taniabulhoes.com.br/000003011_1989_Eau_de_Parfum_80ml_1_b4d4db317b.jpg",
          "alt": "Best Sellers"
        },
        {
          "src": "https://static.taniabulhoes.com.br/000003502_Rosas_Roubadas_Eau_de_Parfum_80ml_1d01905809.jpg",
          "srcset": null,
          "best": "https://static.taniabulhoes.com.br/000003502_Rosas_Roubadas_Eau_de_Parfum_80ml_1d01905809.jpg",
          "alt": null
        },
        {
          "src": "https://static.taniabulhoes.com.br/Encontro_Marcado_Eau_de_Parfum_80ml_2_1_20689c3240.jpg",
          "srcset": null,
          "best": "https://static.taniabulhoes.com.br/Encontro_Marcado_Eau_de_Parfum_80ml_2_1_20689c3240.jpg",
          "alt": "Premiados"
        }
      ],
      "image_urls": [
        "https://static.taniabulhoes.com.br/000003003_Meu_Verde_Eau_de_Parfum_30ml_2_29234c0234.jpg",
        "https://static.taniabulhoes.com.br/000003009_A_Francesa_Eau_de_Parfum_30ml_2_58cba84c8a.jpg",
        "https://static.taniabulhoes.com.br/000003010_Fava_Selvagem_Eau_de_Parfum_30ml_2_fe302c9fdb.jpg",
        "https://static.taniabulhoes.com.br/Encontro_Marcado_Eau_de_Parfum_30ml_7b2fefd524.jpg",
        "https://static.taniabulhoes.com.br/000003015_Cha_Branco_Eau_de_Parfum_80ml_2_d6f39c630f.jpg",
        "https://static.taniabulhoes.com.br/000003011_1989_Eau_de_Parfum_80ml_1_b4d4db317b.jpg",
        "https://static.taniabulhoes.com.br/000003502_Rosas_Roubadas_Eau_de_Parfum_80ml_1d01905809.jpg",
        "https://static.taniabulhoes.com.br/Encontro_Marcado_Eau_de_Parfum_80ml_2_1_20689c3240.jpg"
      ],
      "background_images": [],
      "videos": [],
      "video_urls": [],
      "html": null,
      "score": 829
    },
    {
      "selector": "html[data-sentry-component=\"RootLayout\"] > body:nth-of-type(1) > article:nth-of-type(8)",
      "attrs": {
        "class": "sc-d3b38409-0 lbOpmB"
      },
      "heading": "Famílias Olfativa",
      "text_blocks": [
        "Famílias Olfativa",
        "Nossos perfumes possuem alta concentração dos melhores ingredientes, oferecendo maior durabilidade na pele.",
        "descubra",
        "Frescos",
        "Florais",
        "Amadeirados",
        "Ambarados",
        "Chá Branco"
      ],
      "images": [
        {
          "src": "https://static.taniabulhoes.com.br/000003014_Sinfonia_Eau_de_Parfum_80ml_1_5e8ed34102.jpg",
          "srcset": null,
          "best": "https://static.taniabulhoes.com.br/000003014_Sinfonia_Eau_de_Parfum_80ml_1_5e8ed34102.jpg",
          "alt": "Background image",
          "isBackground": true
        },
        {
          "src": "https://static.taniabulhoes.com.br/000003016_Ventos_de_Lavanda_Eau_de_Parfum_80ml_1_9c137f5014.jpg",
          "srcset": null,
          "best": "https://static.taniabulhoes.com.br/000003016_Ventos_de_Lavanda_Eau_de_Parfum_80ml_1_9c137f5014.jpg",
          "alt": "Background image",
          "isBackground": true
        },
        {
          "src": "https://static.taniabulhoes.com.br/003002800003_Frenesi_Eau_de_Parfum_80ml_2_1_1_ee5fa17959.jpg",
          "srcset": null,
          "best": "https://static.taniabulhoes.com.br/003002800003_Frenesi_Eau_de_Parfum_80ml_2_1_1_ee5fa17959.jpg",
          "alt": "Background image",
          "isBackground": true
        },
        {
          "src": "https://static.taniabulhoes.com.br/000003026_Fava_Selvagem_Eau_de_Parfum_80ml_fc836477e0.jpg",
          "srcset": null,
          "best": "https://static.taniabulhoes.com.br/000003026_Fava_Selvagem_Eau_de_Parfum_80ml_fc836477e0.jpg",
          "alt": "Background image",
          "isBackground": true
        },
        {
          "src": "https://static.taniabulhoes.com.br/000003015_Cha_Branco_Eau_de_Parfum_80ml_1_9cff9443df.jpg",
          "srcset": null,
          "best": "https://static.taniabulhoes.com.br/000003015_Cha_Branco_Eau_de_Parfum_80ml_1_9cff9443df.jpg",
          "alt": "Background image",
          "isBackground": true
        }
      ],
      "image_urls": [
        "https://static.taniabulhoes.com.br/000003014_Sinfonia_Eau_de_Parfum_80ml_1_5e8ed34102.jpg",
        "https://static.taniabulhoes.com.br/000003016_Ventos_de_Lavanda_Eau_de_Parfum_80ml_1_9c137f5014.jpg",
        "https://static.taniabulhoes.com.br/003002800003_Frenesi_Eau_de_Parfum_80ml_2_1_1_ee5fa17959.jpg",
        "https://static.taniabulhoes.com.br/000003026_Fava_Selvagem_Eau_de_Parfum_80ml_fc836477e0.jpg",
        "https://static.taniabulhoes.com.br/000003015_Cha_Branco_Eau_de_Parfum_80ml_1_9cff9443df.jpg"
      ],
      "background_images": [
        "https://static.taniabulhoes.com.br/000003014_Sinfonia_Eau_de_Parfum_80ml_1_5e8ed34102.jpg",
        "https://static.taniabulhoes.com.br/000003016_Ventos_de_Lavanda_Eau_de_Parfum_80ml_1_9c137f5014.jpg",
        "https://static.taniabulhoes.com.br/003002800003_Frenesi_Eau_de_Parfum_80ml_2_1_1_ee5fa17959.jpg",
        "https://static.taniabulhoes.com.br/000003026_Fava_Selvagem_Eau_de_Parfum_80ml_fc836477e0.jpg",
        "https://static.taniabulhoes.com.br/000003015_Cha_Branco_Eau_de_Parfum_80ml_1_9cff9443df.jpg"
      ],
      "videos": [],
      "video_urls": [],
      "html": null,
      "score": 1283
    },
    {
      "selector": "html[data-sentry-component=\"RootLayout\"] > body:nth-of-type(1) > article:nth-of-type(9) > div:nth-of-type(2)",
      "attrs": {
        "class": "sc-7620ef51-2 hqpLLx"
      },
      "heading": null,
      "text_blocks": [
        "Taniapele",
        "Transforme cada dia em uma experiência de spa em casa.",
        "Conheça"
      ],
      "images": [],
      "image_urls": [],
      "background_images": [],
      "videos": [],
      "video_urls": [],
      "html": null,
      "score": 152
    },
    {
      "selector": "html[data-sentry-component=\"RootLayout\"] > body:nth-of-type(1) > article:nth-of-type(10)",
      "attrs": {
        "class": "sc-d3b38409-0 lbOpmB"
      },
      "heading": "Rituais Taniapele",
      "text_blocks": [
        "Rituais Taniapele",
        "Nossas sugestões de rituais de bem-estar, com produtos dedicados a cada momento, para elevar sua rotina de autocuidado.",
        "descubra",
        "Ritual Banho Hidratante",
        "Ritual Super Hidratação",
        "Ritual Viagem Taniapele",
        "Ritual Taniapele",
        "Ritual Bem-estar",
        "Ritual Essenciais Viagem"
      ],
      "images": [
        {
          "src": "https://static.taniabulhoes.com.br/OLEO_BANHO_77936f4510.jpg",
          "srcset": null,
          "best": "https://static.taniabulhoes.com.br/OLEO_BANHO_77936f4510.jpg",
          "alt": "Background image",
          "isBackground": true
        },
        {
          "src": "https://static.taniabulhoes.com.br/ESFOLIANTE_CORPORAL_1_672aa37c8c.jpg",
          "srcset": null,
          "best": "https://static.taniabulhoes.com.br/ESFOLIANTE_CORPORAL_1_672aa37c8c.jpg",
          "alt": "Background image",
          "isBackground": true
        },
        {
          "src": "https://static.taniabulhoes.com.br/RITUAL_VIAGEM_2_dbbfe8af52.jpg",
          "srcset": null,
          "best": "https://static.taniabulhoes.com.br/RITUAL_VIAGEM_2_dbbfe8af52.jpg",
          "alt": "Background image",
          "isBackground": true
        },
        {
          "src": "https://static.taniabulhoes.com.br/Web_1920_6_13_fd58f03903.jpg",
          "srcset": null,
          "best": "https://static.taniabulhoes.com.br/Web_1920_6_13_fd58f03903.jpg",
          "alt": "Background image",
          "isBackground": true
        },
        {
          "src": "https://static.taniabulhoes.com.br/HIDRATANTE_FIRMADOR_4bc53035c7.jpg",
          "srcset": null,
          "best": "https://static.taniabulhoes.com.br/HIDRATANTE_FIRMADOR_4bc53035c7.jpg",
          "alt": "Background image",
          "isBackground": true
        },
        {
          "src": "https://static.taniabulhoes.com.br/SABONETE_LIQUIDO_2_6e2d906158.jpg",
          "srcset": null,
          "best": "https://static.taniabulhoes.com.br/SABONETE_LIQUIDO_2_6e2d906158.jpg",
          "alt": "Background image",
          "isBackground": true
        },
        {
          "src": "https://static.taniabulhoes.com.br/CREME_MAOS_b3da655606.jpg",
          "srcset": null,
          "best": "https://static.taniabulhoes.com.br/CREME_MAOS_b3da655606.jpg",
          "alt": "Background image",
          "isBackground": true
        }
      ],
      "image_urls": [
        "https://static.taniabulhoes.com.br/OLEO_BANHO_77936f4510.jpg",
        "https://static.taniabulhoes.com.br/ESFOLIANTE_CORPORAL_1_672aa37c8c.jpg",
        "https://static.taniabulhoes.com.br/RITUAL_VIAGEM_2_dbbfe8af52.jpg",
        "https://static.taniabulhoes.com.br/Web_1920_6_13_fd58f03903.jpg",
        "https://static.taniabulhoes.com.br/HIDRATANTE_FIRMADOR_4bc53035c7.jpg",
        "https://static.taniabulhoes.com.br/SABONETE_LIQUIDO_2_6e2d906158.jpg",
        "https://static.taniabulhoes.com.br/CREME_MAOS_b3da655606.jpg"
      ],
      "background_images": [
        "https://static.taniabulhoes.com.br/OLEO_BANHO_77936f4510.jpg",
        "https://static.taniabulhoes.com.br/ESFOLIANTE_CORPORAL_1_672aa37c8c.jpg",
        "https://static.taniabulhoes.com.br/RITUAL_VIAGEM_2_dbbfe8af52.jpg",
        "https://static.taniabulhoes.com.br/Web_1920_6_13_fd58f03903.jpg",
        "https://static.taniabulhoes.com.br/HIDRATANTE_FIRMADOR_4bc53035c7.jpg",
        "https://static.taniabulhoes.com.br/SABONETE_LIQUIDO_2_6e2d906158.jpg",
        "https://static.taniabulhoes.com.br/CREME_MAOS_b3da655606.jpg"
      ],
      "videos": [],
      "video_urls": [],
      "html": null,
      "score": 1737
    },
    {
      "selector": "html[data-sentry-component=\"RootLayout\"] > body:nth-of-type(1) > div.sc-5003fafc-0.gKAzof",
      "attrs": {
        "class": "sc-5003fafc-0 gKAzof"
      },
      "heading": "Frete Grátis",
      "text_blocks": [
        "Frete Grátis",
        "A partir de R$ 400,00 em compras.",
        "Compre pelo WhatsApp",
        "+55 (11) 4864-1999",
        "Encontre o presente perfeito",
        "Embalagens especiais para tornar o gesto ainda mais memorável.",
        "Atendimento ao cliente",
        "+55 (11) 94597-2753"
      ],
      "images": [],
      "image_urls": [],
      "background_images": [],
      "videos": [],
      "video_urls": [],
      "html": null,
      "score": 676
    }
  ],
  "scrapedAt": "2025-09-05T13:59:42.644Z",
  "totalSections": 14
}